{
    "benchmark": "ewf",
    "test": "l_g",
    "placement_file": "ewf_496.json",
    "min_cost": 60,
    "placer_cost": 70,
    "router_cost": 72,
    "multicast_max": 3,
    "distances_max": 4,
    "multicasts": {
        "0": 5,
        "1": 28,
        "2": 10,
        "3": 4
    },
    "distances_router": {
        "1": 50,
        "2": 9,
        "4": 1
    },
    "distances_placer": {
        "1": 50,
        "2": 10
    },
    "positions": {
        "40": [
            0,
            1
        ],
        "0": [
            1,
            1
        ],
        "2": [
            1,
            3
        ],
        "3": [
            1,
            4
        ],
        "41": [
            1,
            5
        ],
        "34": [
            2,
            1
        ],
        "38": [
            2,
            3
        ],
        "4": [
            2,
            4
        ],
        "1": [
            2,
            5
        ],
        "36": [
            2,
            6
        ],
        "37": [
            2,
            7
        ],
        "17": [
            3,
            0
        ],
        "35": [
            3,
            1
        ],
        "9": [
            3,
            2
        ],
        "7": [
            3,
            3
        ],
        "5": [
            3,
            4
        ],
        "6": [
            3,
            5
        ],
        "8": [
            3,
            6
        ],
        "11": [
            3,
            7
        ],
        "21": [
            4,
            0
        ],
        "15": [
            4,
            1
        ],
        "12": [
            4,
            2
        ],
        "18": [
            4,
            3
        ],
        "10": [
            4,
            4
        ],
        "13": [
            4,
            5
        ],
        "39": [
            4,
            6
        ],
        "14": [
            4,
            7
        ],
        "42": [
            4,
            8
        ],
        "25": [
            5,
            0
        ],
        "29": [
            5,
            1
        ],
        "46": [
            5,
            2
        ],
        "44": [
            5,
            5
        ],
        "19": [
            5,
            6
        ],
        "16": [
            5,
            7
        ],
        "28": [
            5,
            8
        ],
        "26": [
            6,
            2
        ],
        "22": [
            6,
            3
        ],
        "31": [
            6,
            5
        ],
        "27": [
            6,
            6
        ],
        "20": [
            6,
            7
        ],
        "24": [
            6,
            8
        ],
        "30": [
            7,
            2
        ],
        "32": [
            7,
            3
        ],
        "45": [
            7,
            4
        ],
        "33": [
            7,
            5
        ],
        "23": [
            7,
            6
        ],
        "43": [
            8,
            5
        ]
    },
    "edges": {
        "0_34": {
            "a": "0",
            "b": "34",
            "cost": 1,
            "path": [
                10
            ]
        },
        "1_4": {
            "a": "1",
            "b": "4",
            "cost": 1,
            "path": [
                23
            ]
        },
        "1_36": {
            "a": "1",
            "b": "36",
            "cost": 1,
            "path": [
                23
            ]
        },
        "2_3": {
            "a": "2",
            "b": "3",
            "cost": 1,
            "path": [
                12
            ]
        },
        "2_38": {
            "a": "2",
            "b": "38",
            "cost": 1,
            "path": [
                12
            ]
        },
        "3_4": {
            "a": "3",
            "b": "4",
            "cost": 1,
            "path": [
                13
            ]
        },
        "4_5": {
            "a": "4",
            "b": "5",
            "cost": 1,
            "path": [
                22
            ]
        },
        "5_7": {
            "a": "5",
            "b": "7",
            "cost": 1,
            "path": [
                31
            ]
        },
        "6_8": {
            "a": "6",
            "b": "8",
            "cost": 1,
            "path": [
                32
            ]
        },
        "7_9": {
            "a": "7",
            "b": "9",
            "cost": 1,
            "path": [
                30
            ]
        },
        "7_18": {
            "a": "7",
            "b": "18",
            "cost": 1,
            "path": [
                30
            ]
        },
        "8_11": {
            "a": "8",
            "b": "11",
            "cost": 1,
            "path": [
                33
            ]
        },
        "8_39": {
            "a": "8",
            "b": "39",
            "cost": 1,
            "path": [
                33
            ]
        },
        "9_12": {
            "a": "9",
            "b": "12",
            "cost": 1,
            "path": [
                29
            ]
        },
        "10_13": {
            "a": "10",
            "b": "13",
            "cost": 1,
            "path": [
                40
            ]
        },
        "11_14": {
            "a": "11",
            "b": "14",
            "cost": 1,
            "path": [
                34
            ]
        },
        "12_15": {
            "a": "12",
            "b": "15",
            "cost": 1,
            "path": [
                38
            ]
        },
        "13_44": {
            "a": "13",
            "b": "44",
            "cost": 1,
            "path": [
                41
            ]
        },
        "14_16": {
            "a": "14",
            "b": "16",
            "cost": 1,
            "path": [
                43
            ]
        },
        "15_29": {
            "a": "15",
            "b": "29",
            "cost": 1,
            "path": [
                37
            ]
        },
        "16_19": {
            "a": "16",
            "b": "19",
            "cost": 1,
            "path": [
                52
            ]
        },
        "16_20": {
            "a": "16",
            "b": "20",
            "cost": 1,
            "path": [
                52
            ]
        },
        "16_28": {
            "a": "16",
            "b": "28",
            "cost": 1,
            "path": [
                52
            ]
        },
        "17_21": {
            "a": "17",
            "b": "21",
            "cost": 1,
            "path": [
                27
            ]
        },
        "20_24": {
            "a": "20",
            "b": "24",
            "cost": 1,
            "path": [
                61
            ]
        },
        "21_25": {
            "a": "21",
            "b": "25",
            "cost": 1,
            "path": [
                36
            ]
        },
        "22_26": {
            "a": "22",
            "b": "26",
            "cost": 1,
            "path": [
                57
            ]
        },
        "22_32": {
            "a": "22",
            "b": "32",
            "cost": 1,
            "path": [
                57
            ]
        },
        "23_27": {
            "a": "23",
            "b": "27",
            "cost": 1,
            "path": [
                69
            ]
        },
        "23_33": {
            "a": "23",
            "b": "33",
            "cost": 1,
            "path": [
                69
            ]
        },
        "24_28": {
            "a": "24",
            "b": "28",
            "cost": 1,
            "path": [
                62
            ]
        },
        "25_29": {
            "a": "25",
            "b": "29",
            "cost": 1,
            "path": [
                45
            ]
        },
        "26_30": {
            "a": "26",
            "b": "30",
            "cost": 1,
            "path": [
                56
            ]
        },
        "27_31": {
            "a": "27",
            "b": "31",
            "cost": 1,
            "path": [
                60
            ]
        },
        "28_42": {
            "a": "28",
            "b": "42",
            "cost": 1,
            "path": [
                53
            ]
        },
        "29_46": {
            "a": "29",
            "b": "46",
            "cost": 1,
            "path": [
                46
            ]
        },
        "30_32": {
            "a": "30",
            "b": "32",
            "cost": 1,
            "path": [
                65
            ]
        },
        "31_33": {
            "a": "31",
            "b": "33",
            "cost": 1,
            "path": [
                59
            ]
        },
        "32_45": {
            "a": "32",
            "b": "45",
            "cost": 1,
            "path": [
                66
            ]
        },
        "33_43": {
            "a": "33",
            "b": "43",
            "cost": 1,
            "path": [
                68
            ]
        },
        "34_35": {
            "a": "34",
            "b": "35",
            "cost": 1,
            "path": [
                19
            ]
        },
        "35_17": {
            "a": "35",
            "b": "17",
            "cost": 1,
            "path": [
                28
            ]
        },
        "36_8": {
            "a": "36",
            "b": "8",
            "cost": 1,
            "path": [
                24
            ]
        },
        "36_37": {
            "a": "36",
            "b": "37",
            "cost": 1,
            "path": [
                24
            ]
        },
        "37_11": {
            "a": "37",
            "b": "11",
            "cost": 1,
            "path": [
                25
            ]
        },
        "38_7": {
            "a": "38",
            "b": "7",
            "cost": 1,
            "path": [
                21
            ]
        },
        "39_13": {
            "a": "39",
            "b": "13",
            "cost": 1,
            "path": [
                42
            ]
        },
        "39_19": {
            "a": "39",
            "b": "19",
            "cost": 1,
            "path": [
                42
            ]
        },
        "40_0": {
            "a": "40",
            "b": "0",
            "cost": 1,
            "path": [
                1
            ]
        },
        "41_1": {
            "a": "41",
            "b": "1",
            "cost": 1,
            "path": [
                14
            ]
        },
        "0_2": {
            "a": "0",
            "b": "2",
            "cost": 2,
            "path": [
                10,
                11
            ]
        },
        "4_6": {
            "a": "4",
            "b": "6",
            "cost": 2,
            "path": [
                22,
                23
            ]
        },
        "4_10": {
            "a": "4",
            "b": "10",
            "cost": 2,
            "path": [
                22,
                31
            ]
        },
        "7_10": {
            "a": "7",
            "b": "10",
            "cost": 4,
            "path": [
                30,
                31,
                32,
                41
            ]
        },
        "15_17": {
            "a": "15",
            "b": "17",
            "cost": 2,
            "path": [
                37,
                36
            ]
        },
        "15_18": {
            "a": "15",
            "b": "18",
            "cost": 2,
            "path": [
                37,
                38
            ]
        },
        "18_22": {
            "a": "18",
            "b": "22",
            "cost": 2,
            "path": [
                39,
                48
            ]
        },
        "19_23": {
            "a": "19",
            "b": "23",
            "cost": 2,
            "path": [
                51,
                60
            ]
        },
        "34_15": {
            "a": "34",
            "b": "15",
            "cost": 2,
            "path": [
                19,
                28
            ]
        },
        "38_9": {
            "a": "38",
            "b": "9",
            "cost": 2,
            "path": [
                21,
                20
            ]
        }
    }
}